cpu.v
module cpu(input [7:0]a,input [7:0]b,input clk,output [39:0]result,   output [7:0] pc_out,
    output [3:0] opcode_out);
reg [15:0] memory [0:255];
reg insig;
wire [15:0] instructionregister;
wire [3:0]  op_code;
wire [2:0]  destination;
wire [2:0]  source;
wire [7:0]  address;
wire [7:0] pc;
wire [15:0] instruction;
wire [7:0]new_address;
wire zero_flag;
wire carry_flag;
wire [7:0] reg_a;
wire [7:0] reg_b;
wire halt;
wire [15:0] alu_result;
assign alu_result = result[15:0];
assign pc_out = pc;
assign opcode_out = op_code;
integer i;

initial begin
    for(i=0;i<256;i=i+1)
    memory[i]=16'b0000_000000_000_000;
    memory[0]  = 16'b0010_000000_000_001; // A -> AR1
memory[1]  = 16'b0010_000000_001_010; // B -> AR2

memory[2]  = 16'b0101_000000_001_010; // MUL AR1,AR2
memory[3]  = 16'b1101_000000_000_011; // RESULT -> AR3

memory[4]  = 16'b0100_000000_001_010; // SUB AR1,AR2
memory[5]  = 16'b1101_000000_000_100; // RESULT -> AR4

memory[6]  = 16'b0110_000000_001_010; // DIV AR1,AR2
memory[7]  = 16'b1101_000000_000_101; // RESULT -> AR5

memory[8]  = 16'b0011_000000_011_100; // AR3 + AR4
memory[9]  = 16'b1101_000000_000_110; // RESULT -> AR6

memory[10] = 16'b0011_000000_110_101; // AR6 + AR5
memory[11] = 16'b1101_000000_000_001; // RESULT -> AR1

memory[12] = 16'b1111_000000_000_000; // HALT
end
always @(posedge clk) begin
    insig<=1'b1;
end
assign instruction = memory[pc];
register re(.a(a),.b(b),.memory(instruction),.insig(insig),.clk(clk),.instructionregister(instructionregister),.pc(pc));
controlunit cu(
    .instructionregister(instructionregister),
    .clk(clk),
    .a(a),
    .b(b),
    .alu_result(result[15:0]),
    .new_address(new_address),
    .op_code(op_code),
    .destination(destination),
    .source(source),
    .address(address),
    .reg_a(reg_a),
    .reg_b(reg_b)
);
alu alu(.clk(clk),.a(reg_a),.b(reg_b),.op_code(op_code),.result(result),.zero_flag(zero_flag),.carry_flag(carry_flag));
always @(posedge clk)
begin
    $display("PC=%d OPCODE=%b AR1=%d AR2=%d RESULT=%d",
              pc, op_code, reg_a, reg_b, result);
end
endmodule
module register(input [7:0]a,input [7:0]b,output [7:0]pc,input [15:0]memory,input insig,input clk,output reg [15:0]instructionregister);
reg [7:0]addressregister;
reg [7:0]programcounter;
reg [15:0]memorydataregister;
initial begin
    programcounter = 0;
end
always @(posedge clk)begin
if(insig==1) begin
addressregister<=programcounter;
programcounter<=programcounter+1;
end
end
always @(posedge clk)
begin
    instructionregister <= memory;
end
assign pc = programcounter;
endmodule
module controlunit(
    input [15:0] instructionregister,
    input clk,
    input [7:0] a,
    input [7:0] b,
    input [15:0] alu_result,
    input [7:0] new_address,

    output reg [3:0] op_code,
    output reg [2:0] destination,
    output reg [2:0] source,
    output reg [7:0] address,

    output reg [7:0] reg_a,
    output reg [7:0] reg_b
);

reg [15:0] ar1;
reg [15:0] ar2;
reg [15:0] ar3;
reg [15:0] ar4;
reg [15:0] ar5;
reg [15:0] ar6;

reg halt;

initial begin
    ar1 = 0;
    ar2 = 0;
    ar3 = 0;
    ar4 = 0;
    ar5 = 0;
    ar6 = 0;
    halt = 0;
end

always @(*) begin
    op_code     = instructionregister[15:12];
    address     = instructionregister[11:6];
    source      = instructionregister[5:3];
    destination = instructionregister[2:0];
end

always @(posedge clk) begin
    if(op_code == 4'b1111)
        halt <= 1'b1;
end

always @(posedge clk) begin

    case ({source,destination})

        6'b000001: ar1 <= a;
        6'b000010: ar2 <= a;
        6'b000011: ar3 <= a;
        6'b000100: ar4 <= a;
        6'b000101: ar5 <= a;
        6'b000110: ar6 <= a;

        6'b001001: ar1 <= b;
        6'b001010: ar2 <= b;
        6'b001011: ar3 <= b;
        6'b001100: ar4 <= b;
        6'b001101: ar5 <= b;
        6'b001110: ar6 <= b;

        6'b010010: ar2 <= ar1;
        6'b010011: ar3 <= ar1;
        6'b010100: ar4 <= ar1;
        6'b010101: ar5 <= ar1;
        6'b010110: ar6 <= ar1;

        6'b011001: ar1 <= ar2;
        6'b011011: ar3 <= ar2;
        6'b011100: ar4 <= ar2;
        6'b011101: ar5 <= ar2;
        6'b011110: ar6 <= ar2;

        6'b100001: ar1 <= ar3;
        6'b100010: ar2 <= ar3;
        6'b100100: ar4 <= ar3;
        6'b100101: ar5 <= ar3;
        6'b100110: ar6 <= ar3;

        6'b101001: ar1 <= ar4;
        6'b101010: ar2 <= ar4;
        6'b101011: ar3 <= ar4;
        6'b101101: ar5 <= ar4;
        6'b101110: ar6 <= ar4;

        6'b110001: ar1 <= ar5;
        6'b110010: ar2 <= ar5;
        6'b110011: ar3 <= ar5;
        6'b110100: ar4 <= ar5;
        6'b110110: ar6 <= ar5;

        6'b111001: ar1 <= ar6;
        6'b111010: ar2 <= ar6;
        6'b111011: ar3 <= ar6;
        6'b111100: ar4 <= ar6;
        6'b111101: ar5 <= ar6;

        default: ;

    endcase

end

always @(posedge clk) begin

    if(op_code == 4'b1101) begin

        case(destination)

            3'b001: ar1 <= alu_result;
            3'b010: ar2 <= alu_result;
            3'b011: ar3 <= alu_result;
            3'b100: ar4 <= alu_result;
            3'b101: ar5 <= alu_result;
            3'b110: ar6 <= alu_result;

            default: ;

        endcase

    end

end

always @(*) begin

    case(source)
        3'b001: reg_a = ar1[7:0];
        3'b010: reg_a = ar2[7:0];
        3'b011: reg_a = ar3[7:0];
        3'b100: reg_a = ar4[7:0];
        3'b101: reg_a = ar5[7:0];
        3'b110: reg_a = ar6[7:0];
        default: reg_a = 8'd0;
    endcase

    case(destination)
        3'b001: reg_b = ar1[7:0];
        3'b010: reg_b = ar2[7:0];
        3'b011: reg_b = ar3[7:0];
        3'b100: reg_b = ar4[7:0];
        3'b101: reg_b = ar5[7:0];
        3'b110: reg_b = ar6[7:0];
        default: reg_b = 8'd0;
    endcase

end
always @(posedge clk)
begin
    if(op_code == 4'b1101)
    begin
        case(destination)
            3'b001: ar1 <= alu_result;
            3'b010: ar2 <= alu_result;
            3'b011: ar3 <= alu_result;
            3'b100: ar4 <= alu_result;
            3'b101: ar5 <= alu_result;
            3'b110: ar6 <= alu_result;
        endcase
    end
end

endmodule
module alu(input clk,input [7:0]a,input [7:0]b,input [3:0]op_code,output reg [39:0]result,output reg zero_flag,output reg carry_flag);
wire adder_carry;
wire [7:0]sum;
wire [7:0]difference;
wire [7:0]shiftout;
wire [7:0]and_logic;
wire [7:0]or_logic;
wire [7:0]xor_logic;
wire [7:0]nand_logic;
wire [15:0]mul;
wire [7:0]quitient;
wire [7:0]remainder;
wire [7:0]comparitor;
wire [7:0]aiout;
wire [7:0]biout;
wire [7:0]adout;
wire [7:0]bdout;
wire [7:0]alr;
wire [7:0]blr;
wire [15:0]shiftleftout;
wire [15:0]shiftrightout;
wire bit_op;
wire bit_in;
wire bout;
wire [7:0]c;
adder ADD1(.a(a),.b(b),.cin(1'b0),.cout(adder_carry),.sum(sum));
subtractor SUB1(.a(a),.b(b),.difference(difference));
logicoperators LOG1(
    .a(a),
    .b(b),
    .and_logic(and_logic),
    .or_logic(or_logic),
    .xor_logic(xor_logic),
    .nand_logic(nand_logic)
);
multiplier MUL1(
    .a(a),
    .b(b),
    .clk(clk),
    .mul(mul)
);

division DIV1(
    .a(a),
    .b(b),
    .clk(clk),
    .qutient(quitient),
    .remainder(remainder)
);
comparitor com(.a(a),.b(b),.clk(clk),.comparitor(comparitor));
increment inc(.a(a),.b(b),.clk(clk),.aiout(aiout),.biout(biout));
decrement dec(.a(a),.b(b),.clk(clk),.adout(adout),.bdout(bdout));
shiftleft shl(.a(a),.b(b),.clk(clk),.shiftleftout(shiftleftout));
shiftright shr(.a(a),.b(b),.clk(clk),.shiftrightout(shiftrightout));
always @(*) begin
  carry_flag=1'b0;
  zero_flag=1'b1;
    case(op_code)
        4'b0011:begin
         result = {8'b0,sum};
         carry_flag = adder_carry;
         end          
        4'b0100:begin
         result = difference;
         carry_flag = 1'b0;
         end         
        4'b0101: result = mul;          
        4'b0110: result = {quitient,remainder};
        4'b0111: result = {and_logic,xor_logic};          
        4'b1000: result ={ or_logic, nand_logic};         
        4'b1001: result ={shiftleftout,shiftrightout};           
        4'b1010:result={aiout[7:0],biout[7:0]}; 
        4'b1011:result={adout[7:0],bdout[7:0]};
        4'b1100:result=comparitor;
        default: result = result;
    endcase
 if (result == 16'b0)
            zero_flag = 1'b1;
        else
            zero_flag = 1'b0;
    end
endmodule
module adder(input [7:0]a,input [7:0]b,input cin,output cout,output [7:0]sum);
wire [8:0]C;
wire [7:0]g;
wire [7:0]p;
assign C[0]=cin;
assign g=a&b;
assign p=a^b;
assign C[1]=g[0]|(p[0]&C[0]);
assign C[2]=g[1]|(p[1]&(C[1]));
assign C[3]=g[2]|(p[2]&(C[2]));
assign C[4]=g[3]|(p[3]&(C[3]));
assign C[5]=g[4]|(p[4]&(C[4]));
assign C[6]=g[5]|(p[5]&(C[5]));
assign C[7]=g[6]|(p[6]&(C[6]));
assign C[8]=g[7]|(p[7]&(C[7]));
assign sum=p^C;
assign cout=C[8];
endmodule
module subtractor(input [7:0]a,input [7:0]b,output borrow,output [7:0]difference);
wire [7:0]bn;
wire cout;
assign bn=~b;
adder adder1(.a(a),.b(bn),.sum(difference),.cin(1'b1),.cout(cout));
assign borrow=~cout;
endmodule
module logicoperators(input [7:0]a,input [7:0]b,output [7:0]and_logic,output [7:0]xor_logic,output [7:0]nand_logic,output [7:0]or_logic);
assign and_logic=a&b;
assign or_logic=a|b;
assign nand_logic=~(a&b);
assign xor_logic=a^b;
endmodule

module multiplier(
    input [7:0] a,
    input [7:0] b,
    input clk,
    output reg [15:0] mul
);

reg signed [8:0] A;
reg signed [7:0] Q;
reg signed [8:0] M;

reg Q_1;

integer i;

always @(posedge clk) begin

    A = 9'b0;
    Q = a;
    M = {b[7], b};
    Q_1 = 1'b0;

    for(i=0; i<8; i=i+1) begin

        case({Q[0], Q_1})

            2'b01:
                A = A + M;

            2'b10:
                A = A - M;

            default:
                A = A;

        endcase

        // arithmetic right shift

        Q_1 = Q[0];

        Q = {A[0], Q[7:1]};

        A = {A[8], A[8:1]};

    end

    mul = {A[7:0], Q};

end

endmodule
module division(input [7:0]a,input clk,input [7:0]b,output reg [7:0]qutient,output reg [7:0]remainder);
reg [8:0]int;
reg [7:0]divided;
reg [7:0]divisor;
integer i;
always @(posedge clk)begin
int=9'b0;
divided=a;
divisor=b;
for(i=0;i<8;i=i+1) begin
{int,divided}={int,divided}<<1;
int=int-divisor;
case(int[8])
1'b1: begin
int=int+divisor;
divided[0]=1'b0;
end
1'b0: begin
divided[0]=1'b1;
end
endcase
end
qutient<=divided;
remainder<=int[7:0];
end
endmodule
module comparitor(input [7:0]a,input [7:0]b,input clk,output reg [7:0]comparitor);
always @(posedge clk)begin
if(a>b) begin
comparitor<=8'b10000000;
end
else if(b>a) begin
comparitor<=8'b00000001;
end
else begin
comparitor<=8'b00000000;
end
end
endmodule
module increment(input [7:0]a,input [7:0]b,input clk,output reg [7:0]aiout,output reg [7:0]biout);
always @(posedge clk)begin
aiout<=a+1;
biout<=b+1;
end
endmodule
module decrement(input [7:0]a,input [7:0]b,input clk,output reg [7:0]adout,output reg [7:0]bdout);
always @(posedge clk)begin
adout<=a-1;
bdout<=b-1;
end
endmodule
module shiftleft(input [7:0]a,input [7:0]b,input clk,output reg [15:0]shiftleftout);
reg [7:0]aout;
reg [7:0]bout;
always @(posedge clk)begin
aout<=a<<1;
bout<=b<<1;
shiftleftout<={aout,bout};
end
endmodule
module shiftright(input [7:0]a,input [7:0]b,input clk,output reg [15:0]shiftrightout);
reg [7:0]aout;
reg [7:0]bout;
always @(posedge clk)begin
aout<=a>>1;
bout<=b>>1;
shiftrightout<={aout,bout};
end
endmodule

cpu_tb.v
module cpu_tb;

reg [7:0] a;
reg [7:0] b;
reg clk;

wire [39:0] result;
wire [7:0] pc_out;
wire [3:0] opcode_out;

cpu cpu1(
    .a(a),
    .b(b),
    .clk(clk),
    .result(result),
    .pc_out(pc_out),
    .opcode_out(opcode_out)
);

initial begin
    clk = 1'b0;
    forever #1 clk = ~clk;
end
initial begin
$dumpfile("cpu.vcd");
$dumpvars(0,cpu_tb);
end

initial begin

    a = 8'd8;
    b = 8'd3;

    #100;

    a = 8'd15;
    b = 8'd3;

    #100;

    $finish;
end

initial begin
    $monitor(
    "T=%0t PC=%0d OP=%b RESULT=%0d",
    $time,
    pc_out,
    opcode_out,
    result[15:0]
    );
end

always @(posedge clk) begin
    $display(
    "PC=%0d OP=%b AR1=%0d AR2=%0d AR3=%0d AR4=%0d AR5=%0d AR6=%0d RESULT=%0d",
    cpu1.pc_out,
    cpu1.op_code,
    cpu1.cu.ar1,
    cpu1.cu.ar2,
    cpu1.cu.ar3,
    cpu1.cu.ar4,
    cpu1.cu.ar5,
    cpu1.cu.ar6,
    cpu1.result[15:0]
    );
end

endmodule

cpu.vcd
$date
	Fri Jun  5 22:16:51 2026
$end
$version
	Icarus Verilog
$end
$timescale
	1s
$end
$scope module cpu_tb $end
$var wire 40 ! result [39:0] $end
$var wire 8 " pc_out [7:0] $end
$var wire 4 # opcode_out [3:0] $end
$var reg 8 $ a [7:0] $end
$var reg 8 % b [7:0] $end
$var reg 1 & clk $end
$scope module cpu1 $end
$var wire 8 ' a [7:0] $end
$var wire 8 ( b [7:0] $end
$var wire 1 & clk $end
$var wire 16 ) instruction [15:0] $end
$var wire 8 * new_address [7:0] $end
$var wire 4 + opcode_out [3:0] $end
$var wire 8 , pc_out [7:0] $end
$var wire 1 - zero_flag $end
$var wire 3 . source [2:0] $end
$var wire 40 / result [39:0] $end
$var wire 8 0 reg_b [7:0] $end
$var wire 8 1 reg_a [7:0] $end
$var wire 8 2 pc [7:0] $end
$var wire 4 3 op_code [3:0] $end
$var wire 16 4 instructionregister [15:0] $end
$var wire 3 5 destination [2:0] $end
$var wire 1 6 carry_flag $end
$var wire 16 7 alu_result [15:0] $end
$var wire 8 8 address [7:0] $end
$var reg 1 9 insig $end
$var integer 32 : i [31:0] $end
$scope module alu $end
$var wire 1 & clk $end
$var wire 8 ; xor_logic [7:0] $end
$var wire 8 < sum [7:0] $end
$var wire 16 = shiftrightout [15:0] $end
$var wire 16 > shiftleftout [15:0] $end
$var wire 8 ? remainder [7:0] $end
$var wire 8 @ quitient [7:0] $end
$var wire 8 A or_logic [7:0] $end
$var wire 4 B op_code [3:0] $end
$var wire 8 C nand_logic [7:0] $end
$var wire 16 D mul [15:0] $end
$var wire 8 E difference [7:0] $end
$var wire 8 F comparitor [7:0] $end
$var wire 8 G biout [7:0] $end
$var wire 8 H bdout [7:0] $end
$var wire 8 I b [7:0] $end
$var wire 8 J and_logic [7:0] $end
$var wire 8 K aiout [7:0] $end
$var wire 8 L adout [7:0] $end
$var wire 1 M adder_carry $end
$var wire 8 N a [7:0] $end
$var reg 1 6 carry_flag $end
$var reg 40 O result [39:0] $end
$var reg 1 - zero_flag $end
$scope module ADD1 $end
$var wire 1 P cin $end
$var wire 8 Q g [7:0] $end
$var wire 8 R p [7:0] $end
$var wire 8 S sum [7:0] $end
$var wire 1 M cout $end
$var wire 8 T b [7:0] $end
$var wire 8 U a [7:0] $end
$var wire 9 V C [8:0] $end
$upscope $end
$scope module DIV1 $end
$var wire 1 & clk $end
$var wire 8 W b [7:0] $end
$var wire 8 X a [7:0] $end
$var reg 8 Y divided [7:0] $end
$var reg 8 Z divisor [7:0] $end
$var reg 9 [ int [8:0] $end
$var reg 8 \ qutient [7:0] $end
$var reg 8 ] remainder [7:0] $end
$var integer 32 ^ i [31:0] $end
$upscope $end
$scope module LOG1 $end
$var wire 8 _ and_logic [7:0] $end
$var wire 8 ` nand_logic [7:0] $end
$var wire 8 a or_logic [7:0] $end
$var wire 8 b xor_logic [7:0] $end
$var wire 8 c b [7:0] $end
$var wire 8 d a [7:0] $end
$upscope $end
$scope module MUL1 $end
$var wire 1 & clk $end
$var wire 8 e b [7:0] $end
$var wire 8 f a [7:0] $end
$var reg 9 g A [8:0] $end
$var reg 9 h M [8:0] $end
$var reg 8 i Q [7:0] $end
$var reg 1 j Q_1 $end
$var reg 16 k mul [15:0] $end
$var integer 32 l i [31:0] $end
$upscope $end
$scope module SUB1 $end
$var wire 8 m bn [7:0] $end
$var wire 1 n borrow $end
$var wire 8 o difference [7:0] $end
$var wire 1 p cout $end
$var wire 8 q b [7:0] $end
$var wire 8 r a [7:0] $end
$scope module adder1 $end
$var wire 8 s b [7:0] $end
$var wire 1 t cin $end
$var wire 8 u g [7:0] $end
$var wire 8 v p [7:0] $end
$var wire 8 w sum [7:0] $end
$var wire 1 p cout $end
$var wire 8 x a [7:0] $end
$var wire 9 y C [8:0] $end
$upscope $end
$upscope $end
$scope module com $end
$var wire 1 & clk $end
$var wire 8 z b [7:0] $end
$var wire 8 { a [7:0] $end
$var reg 8 | comparitor [7:0] $end
$upscope $end
$scope module dec $end
$var wire 1 & clk $end
$var wire 8 } b [7:0] $end
$var wire 8 ~ a [7:0] $end
$var reg 8 !" adout [7:0] $end
$var reg 8 "" bdout [7:0] $end
$upscope $end
$scope module inc $end
$var wire 1 & clk $end
$var wire 8 #" b [7:0] $end
$var wire 8 $" a [7:0] $end
$var reg 8 %" aiout [7:0] $end
$var reg 8 &" biout [7:0] $end
$upscope $end
$scope module shl $end
$var wire 1 & clk $end
$var wire 8 '" b [7:0] $end
$var wire 8 (" a [7:0] $end
$var reg 8 )" aout [7:0] $end
$var reg 8 *" bout [7:0] $end
$var reg 16 +" shiftleftout [15:0] $end
$upscope $end
$scope module shr $end
$var wire 1 & clk $end
$var wire 8 ," b [7:0] $end
$var wire 8 -" a [7:0] $end
$var reg 8 ." aout [7:0] $end
$var reg 8 /" bout [7:0] $end
$var reg 16 0" shiftrightout [15:0] $end
$upscope $end
$upscope $end
$scope module cu $end
$var wire 8 1" a [7:0] $end
$var wire 16 2" alu_result [15:0] $end
$var wire 8 3" b [7:0] $end
$var wire 1 & clk $end
$var wire 8 4" new_address [7:0] $end
$var wire 16 5" instructionregister [15:0] $end
$var reg 8 6" address [7:0] $end
$var reg 16 7" ar1 [15:0] $end
$var reg 16 8" ar2 [15:0] $end
$var reg 16 9" ar3 [15:0] $end
$var reg 16 :" ar4 [15:0] $end
$var reg 16 ;" ar5 [15:0] $end
$var reg 16 <" ar6 [15:0] $end
$var reg 3 =" destination [2:0] $end
$var reg 1 >" halt $end
$var reg 4 ?" op_code [3:0] $end
$var reg 8 @" reg_a [7:0] $end
$var reg 8 A" reg_b [7:0] $end
$var reg 3 B" source [2:0] $end
$upscope $end
$scope module re $end
$var wire 8 C" a [7:0] $end
$var wire 8 D" b [7:0] $end
$var wire 1 & clk $end
$var wire 1 9 insig $end
$var wire 16 E" memory [15:0] $end
$var wire 8 F" pc [7:0] $end
$var reg 8 G" addressregister [7:0] $end
$var reg 16 H" instructionregister [15:0] $end
$var reg 8 I" programcounter [7:0] $end
$upscope $end
$upscope $end
$upscope $end
$enddefinitions $end
$comment Show the parameter values. $end
$dumpall
$end
#0
$dumpvars
b0 I"
bx H"
bx G"
b0 F"
b10000000000001 E"
b11 D"
b1000 C"
bx B"
b0 A"
b0 @"
bx ?"
0>"
bx ="
b0 <"
b0 ;"
b0 :"
b0 9"
b0 8"
b0 7"
bx 6"
bx 5"
bz 4"
b11 3"
bx 2"
b1000 1"
bx 0"
bx /"
bx ."
b0 -"
b0 ,"
bx +"
bx *"
bx )"
b0 ("
b0 '"
bx &"
bx %"
b0 $"
b0 #"
bx ""
bx !"
b0 ~
b0 }
bx |
b0 {
b0 z
b111111111 y
b0 x
b0 w
b11111111 v
b0 u
1t
b11111111 s
b0 r
b0 q
1p
b0 o
0n
b11111111 m
bx l
bx k
xj
bx i
bx h
bx g
b0 f
b0 e
b0 d
b0 c
b0 b
b0 a
b11111111 `
b0 _
bx ^
bx ]
bx \
bx [
bx Z
bx Y
b0 X
b0 W
b0 V
b0 U
b0 T
b0 S
b0 R
b0 Q
0P
bx O
b0 N
0M
bx L
bx K
b0 J
b0 I
bx H
bx G
bx F
b0 E
bx D
b11111111 C
bx B
b0 A
bx @
bx ?
bx >
bx =
b0 <
b0 ;
b100000000 :
x9
bx 8
bx 7
06
bx 5
bx 4
bx 3
b0 2
b0 1
b0 0
bx /
bx .
0-
b0 ,
bx +
bz *
b10000000000001 )
b11 (
b1000 '
0&
b11 %
b1000 $
bx #
b0 "
bx !
$end
#1
b1 5
b1 ="
b0 .
b0 B"
b0 8
b0 6"
b10 #
b10 +
b10 3
b10 B
b10 ?"
b10000000000001 4
b10000000000001 5"
b10000000000001 H"
b0 ?
b0 ]
b11111111 @
b11111111 \
b0 F
b0 |
b1 G
b1 &"
b1 K
b1 %"
b11111111 H
b11111111 ""
b11111111 L
b11111111 !"
b0 *"
b0 )"
b0 /"
b0 ."
19
0-
b0 D
b0 k
b1000 l
0j
b0 h
b0 i
b0 g
b1000 ^
b0 Z
b11111111 Y
b0 [
1&
#2
0&
#3
1n
0p
b1111 y
b11111000 E
b11111000 o
b11111000 w
b1000 <
b1000 S
b11110111 v
b11110111 m
b11110111 s
b1000 ;
b1000 b
b1000 A
b1000 a
b1000 R
0-
b1000 0
b1000 I
b1000 T
b1000 W
b1000 c
b1000 e
b1000 q
b1000 z
b1000 }
b1000 #"
b1000 '"
b1000 ,"
b1000 A"
b0 =
b0 0"
b0 >
b0 +"
b1000 7"
b10000000001010 )
b10000000001010 E"
b1 "
b1 ,
b1 2
b1 F"
b1 I"
b0 G"
b1000 ^
b11111111 Y
b1000 l
1&
#4
0&
#5
0n
1p
b111111111 y
b1000 E
b1000 o
b1000 w
b1000 u
b11111111 m
b11111111 s
b11110111 v
b0 0
b0 I
b0 T
b0 W
b0 c
b0 e
b0 q
b0 z
b0 }
b0 #"
b0 '"
b0 ,"
b0 A"
b1000 1
b1000 N
b1000 U
b1000 X
b1000 d
b1000 f
b1000 r
b1000 x
b1000 {
b1000 ~
b1000 $"
b1000 ("
b1000 -"
b1000 @"
b10 5
b10 ="
b1 .
b1 B"
0-
b101000000001010 )
b101000000001010 E"
b10 "
b10 ,
b10 2
b10 F"
b10 I"
b1 G"
b10000000001010 4
b10000000001010 5"
b10000000001010 H"
b0 @
b0 \
b1 F
b1 |
b1001 G
b1001 &"
b111 H
b111 ""
b10000 *"
b100 /"
b1000 l
b1000 h
b0 [
b1000 ^
b1000 Z
b0 Y
1&
#6
0&
#7
b111110001 y
b101 E
b101 o
b101 w
b1011 <
b1011 S
b11110100 v
b0 2"
b0 7
b11111100 m
b11111100 s
b1011 ;
b1011 b
b1011 A
b1011 a
b1011 R
b0 !
b0 /
b0 O
1-
b11 0
b11 I
b11 T
b11 W
b11 c
b11 e
b11 q
b11 z
b11 }
b11 #"
b11 '"
b11 ,"
b11 A"
b101 #
b101 +
b101 3
b101 B
b101 ?"
b100 =
b100 0"
b0 /"
b100 ."
b10000 >
b10000 +"
b0 *"
b10000 )"
b11111111 H
b11111111 ""
b111 L
b111 !"
b1 G
b1 &"
b1001 K
b1001 %"
b10000000 F
b10000000 |
b1000 ?
b1000 ]
b11111111 @
b11111111 \
b11 8"
b101000000001010 4
b101000000001010 5"
b101000000001010 H"
b1101000000000011 )
b1101000000000011 E"
b11 "
b11 ,
b11 2
b11 F"
b11 I"
b10 G"
b1000 [
b1000 ^
b0 Z
b11111111 Y
0j
b1000 l
b0 h
b0 i
1&
#8
0&
#9
0n
1p
b0 E
b0 o
b0 w
b111111111 y
b0 <
b0 S
b11111111 m
b11111111 s
b11111111 v
b0 u
b0 ;
b0 b
b0 A
b0 a
b0 R
b0 0
b0 I
b0 T
b0 W
b0 c
b0 e
b0 q
b0 z
b0 }
b0 #"
b0 '"
b0 ,"
b0 A"
b0 1
b0 N
b0 U
b0 X
b0 d
b0 f
b0 r
b0 x
b0 {
b0 ~
b0 $"
b0 ("
b0 -"
b0 @"
b11 5
b11 ="
b0 .
b0 B"
b1101 #
b1101 +
b1101 3
b1101 B
b1101 ?"
b100000000001010 )
b100000000001010 E"
b100 "
b100 ,
b100 2
b100 F"
b100 I"
b11 G"
b1101000000000011 4
b1101000000000011 5"
b1101000000000011 H"
b10 ?
b10 ]
b10 @
b10 \
b100 G
b100 &"
b10 H
b10 ""
b1000000000000 >
b1000000000000 +"
b110 *"
b10000000000 =
b10000000000 0"
b1 /"
b11000 2"
b11000 7
0-
b11000 !
b11000 /
b11000 O
b11000 D
b11000 k
0j
b0 g
b1000 l
b11 h
b11000 i
b1000 ^
b11 Z
b10 Y
b10 [
1&
#10
0&
#11
b111110001 y
b101 E
b101 o
b101 w
b1011 <
b1011 S
b101 2"
b101 7
b11111100 m
b11111100 s
b11110100 v
b1000 u
b1011 ;
b1011 b
b1011 A
b1011 a
b1011 R
b101 !
b101 /
b101 O
b11 0
b11 I
b11 T
b11 W
b11 c
b11 e
b11 q
b11 z
b11 }
b11 #"
b11 '"
b11 ,"
b11 A"
b1000 1
b1000 N
b1000 U
b1000 X
b1000 d
b1000 f
b1000 r
b1000 x
b1000 {
b1000 ~
b1000 $"
b1000 ("
b1000 -"
b1000 @"
b10 5
b10 ="
b1 .
b1 B"
b100 #
b100 +
b100 3
b100 B
b100 ?"
b10000000001 =
b10000000001 0"
b0 /"
b0 ."
b1000000000110 >
b1000000000110 +"
b0 *"
b0 )"
b11111111 H
b11111111 ""
b11111111 L
b11111111 !"
b1 G
b1 &"
b1 K
b1 %"
b0 F
b0 |
b0 ?
b0 ]
b11111111 @
b11111111 \
b11000 9"
b100000000001010 4
b100000000001010 5"
b100000000001010 H"
b1101000000000100 )
b1101000000000100 E"
b101 "
b101 ,
b101 2
b101 F"
b101 I"
b100 G"
0-
b1000 ^
b0 Z
b11111111 Y
b0 [
b0 D
b0 k
b1000 l
b0 h
b0 i
1&
#12
0&
#13
0n
1p
b0 E
b0 o
b0 w
b111111111 y
b0 <
b0 S
b11111111 m
b11111111 s
b11111111 v
b0 u
b0 ;
b0 b
b0 A
b0 a
b0 R
b0 0
b0 I
b0 T
b0 W
b0 c
b0 e
b0 q
b0 z
b0 }
b0 #"
b0 '"
b0 ,"
b0 A"
b0 1
b0 N
b0 U
b0 X
b0 d
b0 f
b0 r
b0 x
b0 {
b0 ~
b0 $"
b0 ("
b0 -"
b0 @"
b100 5
b100 ="
b0 .
b0 B"
b1101 #
b1101 +
b1101 3
b1101 B
b1101 ?"
b110000000001010 )
b110000000001010 E"
b110 "
b110 ,
b110 2
b110 F"
b110 I"
b101 G"
b1101000000000100 4
b1101000000000100 5"
b1101000000000100 H"
b10 ?
b10 ]
b10 @
b10 \
b10000000 F
b10000000 |
b100 G
b100 &"
b1001 K
b1001 %"
b10 H
b10 ""
b111 L
b111 !"
b0 >
b0 +"
b110 *"
b10000 )"
b0 =
b0 0"
b1 /"
b100 ."
0-
b11000 D
b11000 k
0j
b0 g
b1000 l
b11 h
b11000 i
b10 [
b1000 ^
b11 Z
b10 Y
1&
#14
0&
#15
b111110001 y
b101 E
b101 o
b101 w
b1011 <
b1011 S
b1111111100000000 2"
b1111111100000000 7
b11111100 m
b11111100 s
b11110100 v
b1000 u
b1011 ;
b1011 b
b1011 A
b1011 a
b1011 R
b1111111100000000 !
b1111111100000000 /
b1111111100000000 O
b11 0
b11 I
b11 T
b11 W
b11 c
b11 e
b11 q
b11 z
b11 }
b11 #"
b11 '"
b11 ,"
b11 A"
b1000 1
b1000 N
b1000 U
b1000 X
b1000 d
b1000 f
b1000 r
b1000 x
b1000 {
b1000 ~
b1000 $"
b1000 ("
b1000 -"
b1000 @"
b10 5
b10 ="
b1 .
b1 B"
b110 #
b110 +
b110 3
b110 B
b110 ?"
b10000000001 =
b10000000001 0"
b0 /"
b0 ."
b1000000000110 >
b1000000000110 +"
b0 *"
b0 )"
b11111111 H
b11111111 ""
b11111111 L
b11111111 !"
b1 G
b1 &"
b1 K
b1 %"
b0 F
b0 |
b0 ?
b0 ]
b11111111 @
b11111111 \
b101 :"
b110000000001010 4
b110000000001010 5"
b110000000001010 H"
b1101000000000101 )
b1101000000000101 E"
b111 "
b111 ,
b111 2
b111 F"
b111 I"
b110 G"
0-
b1000 ^
b0 Z
b11111111 Y
b0 [
b0 D
b0 k
b1000 l
b0 h
b0 i
1&
#16
0&
#17
0n
1p
b0 E
b0 o
b0 w
b111111111 y
b0 <
b0 S
b11111111 m
b11111111 s
b11111111 v
b0 u
b0 ;
b0 b
b0 A
b0 a
b0 R
b0 0
b0 I
b0 T
b0 W
b0 c
b0 e
b0 q
b0 z
b0 }
b0 #"
b0 '"
b0 ,"
b0 A"
b0 1
b0 N
b0 U
b0 X
b0 d
b0 f
b0 r
b0 x
b0 {
b0 ~
b0 $"
b0 ("
b0 -"
b0 @"
b1000000010 2"
b1000000010 7
b101 5
b101 ="
b0 .
b0 B"
b1101 #
b1101 +
b1101 3
b1101 B
b1101 ?"
b1000000010 !
b1000000010 /
b1000000010 O
b11000000011100 )
b11000000011100 E"
b1000 "
b1000 ,
b1000 2
b1000 F"
b1000 I"
b111 G"
b1101000000000101 4
b1101000000000101 5"
b1101000000000101 H"
b10 ?
b10 ]
b10 @
b10 \
b10000000 F
b10000000 |
b100 G
b100 &"
b1001 K
b1001 %"
b10 H
b10 ""
b111 L
b111 !"
b0 >
b0 +"
b110 *"
b10000 )"
b0 =
b0 0"
b1 /"
b100 ."
0-
b11000 D
b11000 k
0j
b0 g
b1000 l
b11 h
b11000 i
b10 [
b1000 ^
b11 Z
b10 Y
1&
#18
0&
